adb_connector_python/connector.py
adb_connector_python-1.2.0.dist-info/LICENSE
adb_connector_python-1.2.0.dist-info/METADATA
adb_connector_python-1.2.0.dist-info/WHEEL
adb_connector_python-1.2.0.dist-info/top_level.txt
adb_connector_python-1.2.0.dist-info/RECORD
