Metadata-Version: 2.1
Name: adb-connector-python
Version: 1.2.0
Summary: A simple python package to interface with adb
Author: Giuseppe Gravante
License: MIT License
Project-URL: repository, https://github.com/Giuseppe7887/py-adb
Requires-Python: >=3.7
License-File: LICENSE
Requires-Dist: termcolor
